<annotation>
	<folder>raw</folder>
	<filename>17EF8D00-D112-4379-A4C3-85E6C9EE0EBD - Fadhilah Mileanasari.jpg.jpg</filename>
	<path>C:\Users\mitasofiabdillah\Videos\object_detection_demo-master\data\raw\17EF8D00-D112-4379-A4C3-85E6C9EE0EBD - Fadhilah Mileanasari.jpg.jpg</path>
	<source>
		<database>Unknown</database>
	</source>
	<size>
		<width>3024</width>
		<height>4032</height>
		<depth>3</depth>
	</size>
	<segmented>0</segmented>
	<object>
		<name>person</name>
		<pose>Unspecified</pose>
		<truncated>0</truncated>
		<difficult>0</difficult>
		<bndbox>
			<xmin>962</xmin>
			<ymin>585</ymin>
			<xmax>2431</xmax>
			<ymax>3641</ymax>
		</bndbox>
	</object>
	<object>
		<name>person</name>
		<pose>Unspecified</pose>
		<truncated>0</truncated>
		<difficult>0</difficult>
		<bndbox>
			<xmin>2456</xmin>
			<ymin>572</ymin>
			<xmax>3018</xmax>
			<ymax>2035</ymax>
		</bndbox>
	</object>
</annotation>
